LICENSE
MANIFEST.in
README.md
requirements.txt
setup.py
fleaflicker/__init__.py
fleaflicker/_version.py
fleaflicker/app.properties
fleaflicker.egg-info/PKG-INFO
fleaflicker.egg-info/SOURCES.txt
fleaflicker.egg-info/dependency_links.txt
fleaflicker.egg-info/requires.txt
fleaflicker.egg-info/top_level.txt
fleaflicker/api/FleaflickerAPIClient.py
fleaflicker/api/LeagueInfoAPIClient.py
fleaflicker/api/PlayerAPIClient.py
fleaflicker/api/ScoringAPIClient.py
fleaflicker/api/TeamAPIClient.py
fleaflicker/api/UserAPIClient.py
fleaflicker/api/__init__.py
fleaflicker/enum/Sport.py
fleaflicker/enum/__init__.py
fleaflicker/util/ConfigReader.py
fleaflicker/util/__init__.py